RENA-0.1b1.dist-info/DESCRIPTION.rst
RENA-0.1b1.dist-info/METADATA
RENA-0.1b1.dist-info/RECORD
RENA-0.1b1.dist-info/WHEEL
RENA-0.1b1.dist-info/metadata.json
RENA-0.1b1.dist-info/top_level.txt
rena/DB.py
rena/__init__.py
rena/context.py
rena/crash.py
rena/deduper.py
rena/payload.py
rena/pcap.py
rena/pcaploader.py
