Metadata-Version: 2.0
Name: RENA
Version: 0.1b1
Summary: pcap file framework for CTF
Home-page: https://github.com/Septyem/RENA
Author: Septyem
Author-email: hxma011[spam]gmail.com
License: MIT
Keywords: pcap CTF
Platform: UNKNOWN
